pyinfra_tinc/__init__.py
pyinfra_tinc/defaults.py
pyinfra_tinc/tinc.py
pyinfra_tinc/scripts/install_tinc.sh.j2
pyinfra_tinc/templates/tinc-down.j2
pyinfra_tinc/templates/tinc-up.j2
pyinfra_tinc/templates/tinc.conf.j2
pyinfra_tinc/templates/tinc.service.j2
pyinfra_tinc-0.1.1.dist-info/LICENSE.md
pyinfra_tinc-0.1.1.dist-info/METADATA
pyinfra_tinc-0.1.1.dist-info/WHEEL
pyinfra_tinc-0.1.1.dist-info/top_level.txt
pyinfra_tinc-0.1.1.dist-info/RECORD
