Metadata-Version: 2.1
Name: pyinfra-tinc
Version: 0.1.1
Summary: Install & configure the Tinc mesh VPN with `pyinfra`.
Home-page: https://github.com/Oxygem/pyinfra-tinc
Author: Oxygem Engineers
Author-email: hello@oxygem.com
License: MIT
Platform: UNKNOWN
Requires-Python: >=3.6
Requires-Dist: pyinfra (~=1.2)
